zealous/__init__.py
zealous/base.py
zealous/exceptions.py
zealous/py.typed
zealous/rpc/__init__.py
zealous/rpc/asyncioq/__init__.py
zealous/rpc/asyncioq/base.py
zealous/rpc/base.py
zealous/rpc/exceptions.py
zealous/schema/__init__.py
zealous/schema/base.py
zealous/typing.py
zealous-0.2.4.dist-info/LICENSE
zealous-0.2.4.dist-info/WHEEL
zealous-0.2.4.dist-info/METADATA
zealous-0.2.4.dist-info/RECORD
