Metadata-Version: 2.1
Name: zealous
Version: 0.2.4
Summary: Zealous Framework
Home-page: https://gitlab.com/python-zealous/zealous
License: MIT
Author: Jonathan Gravel
Author-email: jo@stashed.dev
Requires-Python: >=3.7,<4.0
Classifier: License :: OSI Approved :: MIT License
Classifier: Programming Language :: Python :: 3
Classifier: Programming Language :: Python :: 3.7
Classifier: Programming Language :: Python :: 3.8
Requires-Dist: pydantic (>=1.4,<2.0)
Project-URL: Documentation, https://python-zealous.gitlab.io/zealous/
Project-URL: Repository, https://gitlab.com/python-zealous/zealous
